rarbgapi/__init__.py
rarbgapi/__main__.py
rarbgapi/__version__.py
rarbgapi/leakybucket.py
rarbgapi/rarbgapi.py
RarbgAPI-0.5.0.dist-info/LICENSE
RarbgAPI-0.5.0.dist-info/METADATA
RarbgAPI-0.5.0.dist-info/WHEEL
RarbgAPI-0.5.0.dist-info/entry_points.txt
RarbgAPI-0.5.0.dist-info/top_level.txt
RarbgAPI-0.5.0.dist-info/RECORD
