Metadata-Version: 2.1
Name: RarbgAPI
Version: 0.5.0
Summary: A python3 wrapper for RARBG.to
Home-page: https://github.com/verybada/rarbgapi/
Author: verybada
Author-email: verybada.lin@gmail.com
License: BSD
Keywords: rarbg,rarbg-torrentapi,api,python
Platform: UNKNOWN
Classifier: Programming Language :: Python :: 3
Classifier: License :: OSI Approved :: BSD License
Classifier: Operating System :: OS Independent
License-File: LICENSE
Requires-Dist: requests
Provides-Extra: test
Requires-Dist: flake8 ; extra == 'test'
Requires-Dist: pycodestyle ; extra == 'test'
Requires-Dist: pylint ; extra == 'test'
Requires-Dist: pytest ; extra == 'test'
Requires-Dist: pytest-cov ; extra == 'test'
Requires-Dist: pytest-httpserver ; extra == 'test'
